RISC-V CPU.srcs/sources_1/new/control.v
`timescale 1ns / 1ps
//////////////////////////////////////////////////////////////////////////////////
// Company: 
// Engineer: 
// 
// Create Date: 2024/08/27 14:38:30
// Design Name: 
// Module Name: control
// Project Name: 
// Target Devices: 
// Tool Versions: 
// Description: 
// 
// Dependencies: 
// 
// Revision:
// Revision 0.01 - File Created
// Additional Comments:
// 
//////////////////////////////////////////////////////////////////////////////////


module control(
    input clk,
    input rst,
    input zero,
    input[31:0] instruction,
    output reg [3:0] alu_opt,
    output reg branch,
    output reg jalr,
    output reg write_PC4,
    output reg alusrc,
    output reg mem2reg,
    output reg memread,
    output reg memwrite,
    output reg regwrite
    
    );
    // define data type 
    parameter R_TYPE = 3'b000;
    parameter I_TYPE = 3'b001;
    parameter S_TYPE = 3'b010;
    parameter B_TYPE = 3'b011;
    parameter JUMP   = 3'b100;
    parameter UNKNOWN_TYPE = 3'b111;
    
    wire [6:0] opcode ; 
    wire [2:0] funct3 ; 
    wire [6:0] funct7 ; 
    
    reg [2:0] data_type_reg ; 
    
    assign data_type = data_type_reg ; 
        
    assign opcode = instruction[6:0] ; 
    assign funct3 = instruction[14:12] ; 
    assign funct7 = instruction[31:25] ; 
    
    always @( opcode or funct3 or funct7 ) begin 
        case (opcode)
            7'b0110011 : data_type_reg = R_TYPE ; 
            7'b0000011 : data_type_reg = I_TYPE ;   //lw
            7'b0010011 : data_type_reg = I_TYPE ;   //common I_type
            7'b1100111 : data_type_reg = I_TYPE ;   //JALR
            7'b0100011 : data_type_reg = S_TYPE ;   //sw
            7'b1100011 : data_type_reg = B_TYPE ; 
            7'b1101111 : data_type_reg = JUMP ;
            default  : data_type_reg = UNKNOWN_TYPE ; 
        endcase
    end 
    
   always @(opcode or funct3 or funct7) begin
        case (opcode)
           7'b0110011 : //  R_TYPE
                case ({funct7, funct3})
                   10'b0000000_000 : alu_opt = 4'b0000; // add
                   10'b0100000_000 : alu_opt = 4'b0001; // sub
                   10'b0000000_111 : alu_opt = 4'b0111; // and
                   10'b0000000_110 : alu_opt = 4'b0110; // or
                   10'b0000000_100 : alu_opt = 4'b0100; // xor
                   10'b0000000_001 : alu_opt = 4'b0010; // sll
                   10'b0000000_101 : alu_opt = 4'b0101; // srl
                    default: alu_opt = 4'bxxxx;
                endcase
           7'b0010011 : //   I_TYPE
                case ({funct3})
                   3'b000 : alu_opt = 4'b0000; // addi
                   3'b100 : alu_opt = 4'b0100; // xori
                   3'b110 : alu_opt = 4'b0110; // ori
                   3'b111 : alu_opt = 4'b0111; // andi
                   3'b001 : alu_opt = 4'b0010; // slli
                   3'b101 : alu_opt = 4'b0101; // srli
                    default: alu_opt = 4'bxxxx;
                endcase
           7'b0000011 : alu_opt = 4'b0000; // lw
           7'b0100011 : alu_opt = 4'b0000; // sw
           7'b1100111 : alu_opt = 4'b0000; // jalr
           7'b1101111 : alu_opt = 4'b0000; // jal
           7'b1100011 : alu_opt = 4'b0001; // beq¡Bbne¡Bblt¡Bbge
            default: alu_opt = 4'bxxxx;
        endcase
    end
        
    always @(data_type_reg) begin 
        branch = 0 ;
        jalr = 0 ; 
        write_PC4 = 0 ; 
        alusrc = 0 ; 
        mem2reg = 0 ; 
        memread = 0 ; 
        memwrite = 0 ; 
        regwrite = 0 ; 
        
        case (data_type_reg)
            R_TYPE : regwrite = 1 ; 
    
            I_TYPE : 
                case (opcode)
                    7'b0000011 : begin // lw
                        memread = 1 ; 
                        mem2reg = 1 ;
                        regwrite = 1 ; 
                        alusrc = 1 ; 
                    end
                    7'b0010011 : begin // commonI
                        regwrite = 1 ;    
                        alusrc = 1 ;
                    end
                    7'b1100111 : begin // JALR
                        jalr = 1 ; 
                        write_PC4 = 1 ; 
                    end
                    default : begin
                        regwrite = 1 ;    
                        alusrc = 1 ;
                    end
                endcase
    
            S_TYPE : begin             
                memwrite = 1 ;
                alusrc = 1 ;
            end
    
            B_TYPE : 
                case ({funct3, zero})
                    4'b000_1 : branch = 1; // beq
                    4'b001_0 : branch = 1; // bne
                    4'b100_0 : branch = 1; // blt
                    4'b101_0 : branch = 1; // bge (Á×§Kx)
                    default: branch = 0;
                endcase
    
            JUMP : begin
                jalr = 1 ;
                write_PC4 = 1 ;
            end
            
            default: begin
                $display("Error: UNKNOWN_TYPE detected for data_type_reg = %b", data_type_reg);
            end
        endcase
    end

    
    /*
    assign data_type = ( opcode == 7'b0110011 ) ? R_TYPE : 
                        ( opcode == 7'b0000011 ||  opcode == 7'b0010011) ? I_TYPE : 
                        ( opcode == 7'b0100011 ) ? S_TYPE : 
                        ( opcode == 7'b1100011 ) ? B_TYPE :
                        ( opcode == 7'b1100011 ) ? B_TYPE : 
                        ( opcode == 7'b1100011 ) ? JUMP : 3'd0 ;  
    */
    
endmodule

RISC-V CPU.srcs/sources_1/new/memory_access.v
`timescale 1ns / 1ps

module memory_access(
    input clk,
    input rst, 
    input [31:0] data_in,
    input [31:0] data_address,
    input mem2reg, 
    input memwrite,
    input memread,
    output [31:0] read_data
    );
    
    reg [31:0] data_memory[0:31] ; 
    integer i ; 
    
    assign read_data = (mem2reg) ? data_memory[data_address] : data_address ; 
    
    always@(posedge clk or posedge rst) begin 
        if (rst) begin
            for(i=0; i<32; i=i+1) begin
                data_memory[i] <= 32'd0 ; 
            end
        end
        if (memwrite) data_memory[data_address] <= data_in ; 
        else data_memory[data_address] <= data_memory[data_address] ;
    end
    
endmodule

RISC-V CPU.srcs/sources_1/new/execution.v
`timescale 1ns / 1ps

module execution(
    input [31:0] alu1,
    input [31:0] alu2,
    input [3:0] alu_opt,
    output [31:0] alu_out,
    output zero
    );
    
    
    reg [31:0] alu_temp ; 
    assign alu_out = alu_temp ;
    assign zero = (alu_out == 32'd0 ) ? 1 : 0 ;  
    
    always@(*) begin 
        case(alu_opt) 
            4'b0000 : alu_temp = alu1 + alu2 ;          //ADD
            4'b0001 : alu_temp = alu1 - alu2 ;          //SUB
            4'b0010 : alu_temp = alu1 << alu2 ;         //SLL
            4'b0011 : alu_temp = (alu1 < alu2)?1:0 ;    //SLT
            4'b0100 : alu_temp = alu1 ^ alu2 ;          //XOR
            4'b0101 : alu_temp = alu1 >> alu2 ;         //SRL
            4'b0110 : alu_temp = alu1 | alu2 ;          //OR
            4'b0111 : alu_temp = alu1 & alu2 ;          //AND
            default : alu_temp = 32'hxxxx_xxxx ; 
        endcase
    end
endmodule

RISC-V CPU.srcs/sources_1/new/imm_gen.v
`timescale 1ns / 1ps
//////////////////////////////////////////////////////////////////////////////////
// Company: 
// Engineer: 
// 
// Create Date: 2024/09/12 10:47:13
// Design Name: 
// Module Name: imm_gen
// Project Name: 
// Target Devices: 
// Tool Versions: 
// Description: 
// 
// Dependencies: 
// 
// Revision:
// Revision 0.01 - File Created
// Additional Comments:
// 
//////////////////////////////////////////////////////////////////////////////////


module imm_gen(
    input [11:0] imm_in,
    output [31:0] imm_out
    );
    
    assign imm_out = {{20{imm_in[11]}}, {imm_in[10:0]}} ; 
endmodule

RISC-V CPU.srcs/sources_1/new/register_file.v
module register_file (
    input clk,    
    input rst,           
    input regwrite,               
    input [4:0] read_addr1, 
    input [4:0] read_addr2, 
    input [4:0] write_addr, 
    input [31:0] write_data,
    output [31:0] read_data1,
    output [31:0] read_data2 
);

    reg [31:0] reg_file [0:31];
    integer i ;
    
    assign read_data1 = reg_file[read_addr1]; 
    assign read_data2 = reg_file[read_addr2]; 
    
    always @(posedge clk or posedge rst) begin
        if (rst) begin
            for(i=0; i<32; i=i+1) begin
                reg_file[i] <= 32'd0 ; 
            end
        end
        else if (regwrite)
            reg_file[write_addr] <= write_data; 
        else  reg_file[write_addr] <= reg_file[write_addr]; 
    end

endmodule

RISC-V CPU.srcs/sources_1/new/instruction_decode.v
`timescale 1ns / 1ps

module instruction_decode(
    input clk,
    input rst,
    input[31:0] instruction,
    input [31:0] write_datareg,
    input [31:0] write_datapc,
    input regwrite,
    input alusrc,
    input write_PC4,
    output[31:0] data_a,
    output[31:0] data_b,
    output[31:0] write_dataM
    );
    
    wire [6:0] opcode ; 
    wire [4:0] rs1;
    wire [4:0] rs2;
    wire [4:0] rd;
    wire [31:0] read_data_a;
    wire [31:0] read_data_b;
    wire [31:0] write_data; 
    wire [31:0] imm_out ; 
    wire [11:0] imm_in ; 
    wire [11:0] imm_I ; 
    wire [11:0] imm_S ; 
    wire [11:0] imm_B ;
    
    assign rs1 = instruction[19:15] ; 
    assign rs2 = instruction[24:20] ; 
    assign rd = instruction[11:7] ; 
    assign opcode = instruction[6:0] ; 
    assign imm_I = instruction[31:20] ; 
    assign imm_S = {instruction[31:25],instruction[11:7]} ; 
    assign imm_B = {instruction[31],instruction[7],instruction[30:25],instruction[11:8]} ; 
    
    assign data_a = read_data_a ;  
    assign write_dataM = read_data_b ; 
    assign write_data = (write_PC4) ? write_datapc : write_datareg ; 
    assign data_b = (alusrc) ? imm_out : read_data_b;
    assign imm_in = (opcode == 7'b0100011) ? imm_S : (opcode == 7'b1100011)  ? imm_B : imm_I ; 
    
    register_file u0 (
        .clk(clk),    
        .rst(rst),           
        .regwrite(regwrite),               
        .read_addr1(rs1), 
        .read_addr2(rs2),
        .write_addr(rd), 
        .write_data(write_data),
        .read_data1(read_data_a),
        .read_data2(read_data_b) 
    );
    
    imm_gen u1(
        .imm_in(imm_in),
        .imm_out(imm_out)
    );
    
endmodule

RISC-V CPU.srcs/sources_1/new/instruction_mem.v
`timescale 1ns / 1ps

module instruction_mem(
    input [31:0] instruction_address,
    output [31:0] instruction
    );
    
    reg [31:0] Mem [0:16383];  // 16k * 32bit memeory
    
    assign instruction = Mem[instruction_address / 32'h4];

    initial begin
        $readmemb("C:/vivado/RISC-V CPU/RISC-V CPU.srcs/sources_1/new/Instruction_data.txt", Mem);
    end
endmodule

RISC-V CPU.srcs/sources_1/new/instruction_fetch.v
`timescale 1ns / 1ps

module instruction_fetch(
    input clk,
    input rst,
    input jalr,
    input branch,
    input [31:0] jump_addr,
    output [31:0] pc,
    output [31:0] instruction
    );
    
    wire [31:0] branch_addr ; 
    wire [31:0] PC_offset;
    wire [6:0] opcode = instruction[6:0];
    wire [31:0] imm_B = {{20{instruction[31]}}, instruction[7], instruction[30:25], instruction[11:8], 1'b0};
    wire [31:0] imm_J = {{12{instruction[31]}}, instruction[19:12], instruction[20], instruction[30:21], 1'b0};
    reg [31:0] pc_temp ; 
    
    assign PC_offset = (opcode == 7'b1101111) ? imm_J : imm_B;
    assign branch_addr = (jalr) ? jump_addr : (pc + PC_offset);  
    assign pc = pc_temp ; 
    
    instruction_mem u0 (
        .instruction_address(pc),
        .instruction(instruction)
    );
    
    // program counter 
    always@( posedge clk or posedge rst ) begin 
        if (rst) 
            pc_temp <= 32'd0 ; 
        else if (branch)
            pc_temp <= branch_addr ; 
        else begin
            pc_temp <= pc_temp + 32'd4 ; 
        end
    end
    
endmodule

RISC-V CPU.srcs/sources_1/new/top_mod.v
`timescale 1ns / 1ps

module top_mod(
    input clk,
    input rst,
    output [31:0] pc,
    output [31:0] ins
    );
    
    wire [31:0] instruction ;
    wire [31:0] alu1 ; 
    wire [31:0] alu2 ; 
    wire [3:0] alu_opt ;
    wire [31:0] alu_out ;
    wire [31:0] write_dataM ; 
    wire [31:0] write_datareg ; 
    
    wire zero ; 
    wire jalr ; 
    wire branch ; 
    wire write_PC4 ; 
    wire alusrc ;
    wire mem2reg ; 
    wire regwrite ; 
    
    wire memread ; 
    wire memwrite ; 
    
    assign ins = instruction ; 
    instruction_fetch u0 ( 
        .clk(clk),
        .rst(rst),
        .jalr(jalr),
        .branch(branch),
        .jump_addr(alu_out),
        .pc(pc),
        .instruction(instruction)
    );
    
    instruction_decode u1 (
        .clk(clk),
        .rst(rst),
        .instruction(instruction),
        .write_datareg(write_datareg),
        .write_datapc(pc + 32'd4),
        .regwrite(regwrite),
        .alusrc(alusrc),
        .write_PC4(write_PC4),
        .data_a(alu1),
        .data_b(alu2),
        .write_dataM(write_dataM)
    );
    
    execution u2 ( 
        .alu1(alu1),
        .alu2(alu2),
        .alu_opt(alu_opt),
        .alu_out(alu_out),
        .zero(zero)
    );
    
    memory_access u3 ( 
        .clk(clk),
        .rst(rst),
        .data_in(write_dataM),
        .data_address(alu_out),
        .mem2reg(mem2reg),
        .memwrite(memwrite),
        .memread(memread),
        .read_data(write_datareg)
    );
    
    control u4 ( 
        .clk(clk),
        .rst(rst),
        .zero(zero),
        .instruction(instruction),
        .alu_opt(alu_opt),
        .branch(branch),
        .jalr(jalr),
        .write_PC4(write_PC4),
        .alusrc(alusrc),
        .mem2reg(mem2reg),
        .memread(memread),
        .memwrite(memwrite),
        .regwrite(regwrite)
    );
endmodule

RISC-V CPU.srcs/sim_1/new/tb_top_mod.v
`timescale 1ns/1ps

module tb_top_mod (
);
    reg clk;
    reg reset;
    wire [31:0] pc;
    wire [31:0] ins;

    top_mod uut (
        .clk(clk),
        .rst(reset),
        .pc(pc),
        .ins(ins)
    );

    always #5 clk = ~clk;
    initial begin
        $dumpfile("riscv.vcd");
        $dumpvars(0, tb_top_mod);
        $monitor("PC = 0x%h, Instruction = %b", pc, ins);
        clk = 0;
        reset = 0;

        #1 reset = 1;
        #1 reset = 0;

        #200 $finish;
    end
endmodule

RISC-V CPU.sim/sim_1/behav/xsim/riscv.vcd
$date
   Mon Sep 23 16:59:15 2024
$end
$version
  2020.2
$end
$timescale
  1ps
$end
$scope module tb_top_mod $end
$var reg 1 ! clk $end
$var reg 1 " reset $end
$var wire 32 # pc [31:0] $end
$var wire 32 $ ins [31:0] $end
$scope module uut $end
$var wire 1 % clk $end
$var wire 1 & rst $end
$var wire 32 # pc [31:0] $end
$var wire 32 $ ins [31:0] $end
$var wire 32 ' instruction [31:0] $end
$var wire 32 ( alu1 [31:0] $end
$var wire 32 ) alu2 [31:0] $end
$var wire 4 * alu_opt [3:0] $end
$var wire 32 + alu_out [31:0] $end
$var wire 32 , write_dataM [31:0] $end
$var wire 32 - write_datareg [31:0] $end
$var wire 1 . zero $end
$var wire 1 / jalr $end
$var wire 1 0 branch $end
$var wire 1 1 write_PC4 $end
$var wire 1 2 alusrc $end
$var wire 1 3 mem2reg $end
$var wire 1 4 regwrite $end
$var wire 1 5 memread $end
$var wire 1 6 memwrite $end
$scope module u0 $end
$var wire 1 % clk $end
$var wire 1 & rst $end
$var wire 1 / jalr $end
$var wire 1 0 branch $end
$var wire 32 + jump_addr [31:0] $end
$var wire 32 # pc [31:0] $end
$var wire 32 ' instruction [31:0] $end
$var wire 32 7 branch_addr [31:0] $end
$var wire 32 8 PC_offset [31:0] $end
$var wire 7 9 opcode [6:0] $end
$var wire 32 : imm_B [31:0] $end
$var wire 32 ; imm_J [31:0] $end
$var reg 32 < pc_temp [31:0] $end
$scope module u0 $end
$var wire 32 # instruction_address [31:0] $end
$var wire 32 ' instruction [31:0] $end
$upscope $end
$upscope $end
$scope module u1 $end
$var wire 1 % clk $end
$var wire 1 & rst $end
$var wire 32 ' instruction [31:0] $end
$var wire 32 - write_datareg [31:0] $end
$var wire 32 = write_datapc [31:0] $end
$var wire 1 4 regwrite $end
$var wire 1 2 alusrc $end
$var wire 1 1 write_PC4 $end
$var wire 32 ( data_a [31:0] $end
$var wire 32 ) data_b [31:0] $end
$var wire 32 , write_dataM [31:0] $end
$var wire 7 > opcode [6:0] $end
$var wire 5 ? rs1 [4:0] $end
$var wire 5 @ rs2 [4:0] $end
$var wire 5 A rd [4:0] $end
$var wire 32 B read_data_a [31:0] $end
$var wire 32 C read_data_b [31:0] $end
$var wire 32 D write_data [31:0] $end
$var wire 32 E imm_out [31:0] $end
$var wire 12 F imm_in [11:0] $end
$var wire 12 G imm_I [11:0] $end
$var wire 12 H imm_S [11:0] $end
$var wire 12 I imm_B [11:0] $end
$scope module u0 $end
$var wire 1 % clk $end
$var wire 1 & rst $end
$var wire 1 4 regwrite $end
$var wire 5 ? read_addr1 [4:0] $end
$var wire 5 @ read_addr2 [4:0] $end
$var wire 5 A write_addr [4:0] $end
$var wire 32 D write_data [31:0] $end
$var wire 32 B read_data1 [31:0] $end
$var wire 32 C read_data2 [31:0] $end
$var integer 32 J i $end
$upscope $end
$scope module u1 $end
$var wire 12 F imm_in [11:0] $end
$var wire 32 E imm_out [31:0] $end
$upscope $end
$upscope $end
$scope module u2 $end
$var wire 32 ( alu1 [31:0] $end
$var wire 32 ) alu2 [31:0] $end
$var wire 4 * alu_opt [3:0] $end
$var wire 32 + alu_out [31:0] $end
$var wire 1 . zero $end
$var reg 32 K alu_temp [31:0] $end
$upscope $end
$scope module u3 $end
$var wire 1 % clk $end
$var wire 1 & rst $end
$var wire 32 , data_in [31:0] $end
$var wire 32 + data_address [31:0] $end
$var wire 1 3 mem2reg $end
$var wire 1 6 memwrite $end
$var wire 1 5 memread $end
$var wire 32 - read_data [31:0] $end
$var integer 32 L i $end
$upscope $end
$scope module u4 $end
$var wire 1 % clk $end
$var wire 1 & rst $end
$var wire 1 . zero $end
$var wire 32 ' instruction [31:0] $end
$var reg 4 M alu_opt [3:0] $end
$var reg 1 N branch $end
$var reg 1 O jalr $end
$var reg 1 P write_PC4 $end
$var reg 1 Q alusrc $end
$var reg 1 R mem2reg $end
$var reg 1 S memread $end
$var reg 1 T memwrite $end
$var reg 1 U regwrite $end
$var wire 7 V opcode [6:0] $end
$var wire 3 W funct3 [2:0] $end
$var wire 7 X funct7 [6:0] $end
$var reg 3 Y data_type_reg [2:0] $end
$var wire 1 Z data_type $end
$var parameter 3 [ R_TYPE [2:0] $end
$var parameter 3 \ I_TYPE [2:0] $end
$var parameter 3 ] S_TYPE [2:0] $end
$var parameter 3 ^ B_TYPE [2:0] $end
$var parameter 3 _ JUMP [2:0] $end
$var parameter 3 ` UNKNOWN_TYPE [2:0] $end
$upscope $end
$upscope $end
$upscope $end
$enddefinitions $end
#0
$dumpvars
0!
0"
bx #
bx $
0%
0&
bx '
bx (
bx )
bx *
bx +
bx ,
bx -
x.
x/
x0
x1
x2
x3
x4
x5
x6
bx 7
bx0 8
bx 9
bx0 :
bx0 ;
bx <
bx =
bx >
bx ?
bx @
bx A
bx B
bx C
bx D
b0xxxxxxxxxxxxxxxxxxxxxxxxxxxxxxx E
bx F
bx G
bx H
bx I
bx J
bx K
bx L
bx M
xN
xO
xP
xQ
xR
xS
xT
xU
bx V
bx W
bx X
bx Y
xZ
b0 [
b1 \
b10 ]
b11 ^
b100 _
b111 `
$end
#1000
1"
b0 #
b101000000000000010010011 $
1&
b101000000000000010010011 '
b0 (
b1010 )
b0 *
b1010 +
b0 ,
b1010 -
0.
0/
00
01
12
03
14
05
06
b100000000000 7
b100000000000 8
b10011 9
b100000000000 :
b1010 ;
b0 <
b100 =
b10011 >
b0 ?
b1010 @
b1 A
b0 B
b0 C
b1010 D
b1010 E
b1010 F
b1010 G
b1 H
b10000000000 I
b1010 K
b0 M
0N
0O
0P
1Q
0R
0S
0T
1U
b10011 V
b0 W
b0 X
b1 Y
1Z
#2000
0"
0&
#5000
1!
b100 #
b1100100000000000100010011 $
1%
b1100100000000000100010011 '
b11001 )
b11001 +
b11001 -
b110 7
b10 8
b10 :
b100000011000 ;
b100 <
b1000 =
b11001 @
b10 A
b0 B
b0 C
b11001 D
b11001 E
b11001 F
b11001 G
b10 H
b1 I
b11001 K
#10000
0!
0%
#15000
1!
b1000 #
b11001000000000000110010011 $
1%
b11001000000000000110010011 '
b110010 )
b110010 +
b110010 -
b100000101010 7
b100000100010 8
b100000100010 :
b110010 ;
b1000 <
b1100 =
b10010 @
b11 A
b0 B
b0 C
b110010 D
b110010 E
b110010 F
b110010 G
b100011 H
b10000010001 I
b110010 K
b0 M
b1 X
b1 Y
#20000
0!
0%
#25000
1!
b1100 #
b1000001000001000110011 $
1%
b1000001000001000110011 '
b1010 (
b11001 )
b100011 +
b11001 ,
b100011 -
02
b10000 7
b100 8
b110011 9
b100 :
b1000000000000010 ;
b1100 <
b10000 =
b110011 >
b1 ?
b10 @
b100 A
b1010 B
b11001 C
b100011 D
b10 E
b10 F
b10 G
b100 H
b10 I
b100011 K
b0 M
0N
0O
0P
0Q
0R
0S
0T
1U
b110011 V
b0 X
b0 Y
0Z
#30000
0!
0%
#35000
1!
b10000 #
b1000000000100010000001010110011 $
1%
b1000000000100010000001010110011 '
b11001 (
b1010 )
b1 *
b1111 +
b1010 ,
b1111 -
b110000010100 7
b110000000100 8
b110000000100 :
b10000110000000000 ;
b10000 <
b10100 =
b10 ?
b1 @
b101 A
b11001 B
b1010 C
b1111 D
b10000000001 E
b10000000001 F
b10000000001 G
b10000000101 H
b11000000010 I
b1111 K
b1 M
b100000 X
b0 Y
#40000
0!
0%
#45000
1!
b10100 #
b1000001111001100110011 $
1%
b1000001111001100110011 '
b1010 (
b11001 )
b111 *
b1000 +
b11001 ,
b1000 -
b11010 7
b110 8
b110 :
b1111000000000010 ;
b10100 <
b11000 =
b1 ?
b10 @
b110 A
b1010 B
b11001 C
b1000 D
b10 E
b10 F
b10 G
b110 H
b11 I
b1000 K
b111 M
b111 W
b0 X
b0 Y
#50000
0!
0%
#55000
1!
b11000 #
b1000001110001110110011 $
1%
b1000001110001110110011 '
b110 *
b11011 +
b11011 -
b100000011110 7
b100000000110 8
b100000000110 :
b1110000000000010 ;
b11000 <
b11100 =
b111 A
b1010 B
b11001 C
b11011 D
b10 F
b111 H
b10000000011 I
b11011 K
b110 M
b110 W
b0 Y
#60000
0!
0%
#65000
1!
b11100 #
b10100000010000000100011 $
1%
b10100000010000000100011 '
b0 (
b0 )
b0 *
b0 +
b1111 ,
b0 -
1.
12
04
16
b11100 7
b0 8
b100011 9
b0 :
b10100000000100 ;
b11100 <
b100000 =
b100011 >
b0 ?
b101 @
b0 A
b0 B
b1111 C
b0 D
b0 E
b0 F
b101 G
b0 H
b0 I
b0 K
b0 M
0N
0O
0P
1Q
0R
0S
1T
0U
b100011 V
b10 W
b10 Y
#70000
0!
0%
#75000
1!
b100000 #
b11000000010001000100011 $
1%
b11000000010001000100011 '
b100 )
b100 +
b1000 ,
b100 -
0.
b100100 7
b100 8
b100 :
b10000000000110 ;
b100000 <
b100100 =
b110 @
b100 A
b1000 C
b100 D
b100 E
b100 F
b110 G
b100 H
b10 I
b100 K
#80000
0!
0%
#85000
1!
b100100 #
b10000000010010000100011 $
1%
b10000000010010000100011 '
b1000 )
b1000 +
b100011 ,
b1000 -
b101100 7
b1000 8
b1000 :
b10000000000100 ;
b100100 <
b101000 =
b100 @
b1000 A
b100011 C
b1000 D
b1000 E
b1000 F
b100 G
b1000 H
b100 I
b1000 K
#90000
0!
0%
#95000
1!
b101000 #
b100000000010001110000011 $
1%
b100000000010001110000011 '
b1000 )
b0 ,
b100011 -
12
13
14
15
06
b100000101110 7
b100000000110 8
b11 9
b100000000110 :
b10000000001000 ;
b101000 <
b101100 =
b11 >
b1000 @
b111 A
b0 C
b100011 D
b1000 F
b1000 G
b111 H
b10000000011 I
b0 M
0N
0O
0P
1Q
1R
1S
0T
1U
b11 V
b1 Y
1Z
#100000
0!
0%
#105000
1!
b101100 #
b11111110000111111111000011101111 $
1%
b11111110000111111111000011101111 '
b1010 )
b1010 +
b1010 ,
b1010 -
1/
11
02
03
04
05
b1010 7
b11111111111111111111111111100000 8
b1101111 9
b11111111111111111111111111100000 :
b11111111111111111111111111100000 ;
b101100 <
b110000 =
b1101111 >
b11111 ?
b1 @
b1 A
b0 B
b1010 C
b110000 D
b1111111111111111111111111100001 E
b111111100001 F
b111111100001 G
b111111100001 H
b111111110000 I
b1010 K
b0 M
0N
1O
1P
0Q
0R
0S
0T
0U
b1101111 V
b111 W
b1111111 X
b100 Y
0Z
#110000
0!
0%
#115000
1!
b110000 #
bx $
1%
bx '
bx (
bx )
bx *
bx +
bx ,
bx -
x.
0/
01
bx 7
bx0 8
bx 9
bx0 :
bx0 ;
b110000 <
b110100 =
bx >
bx ?
bx @
bx A
bx B
bx C
bx D
b0xxxxxxxxxxxxxxxxxxxxxxxxxxxxxxx E
bx F
bx G
bx H
bx I
bx K
bx M
0N
0O
0P
0Q
0R
0S
0T
0U
bx V
bx W
bx X
b111 Y
1Z
#120000
0!
0%
#125000
1!
b110100 #
1%
bx '
b110100 <
b111000 =
#130000
0!
0%
#135000
1!
b111000 #
1%
bx '
b111000 <
b111100 =
#140000
0!
0%
#145000
1!
b111100 #
1%
bx '
b111100 <
b1000000 =
#150000
0!
0%
#155000
1!
b1000000 #
1%
bx '
b1000000 <
b1000100 =
#160000
0!
0%
#165000
1!
b1000100 #
1%
bx '
b1000100 <
b1001000 =
#170000
0!
0%
#175000
1!
b1001000 #
1%
bx '
b1001000 <
b1001100 =
#180000
0!
0%
#185000
1!
b1001100 #
1%
bx '
b1001100 <
b1010000 =
#190000
0!
0%
#195000
1!
b1010000 #
1%
bx '
b1010000 <
b1010100 =
